stftpitchshift/__init__.py
stftpitchshift/cepster.py
stftpitchshift/io.py
stftpitchshift/main.py
stftpitchshift/normalizer.py
stftpitchshift/pitcher.py
stftpitchshift/plot.py
stftpitchshift/resampler.py
stftpitchshift/stft.py
stftpitchshift/stftpitchshift.py
stftpitchshift/vocoder.py
stftpitchshift-2.0.dist-info/LICENSE
stftpitchshift-2.0.dist-info/METADATA
stftpitchshift-2.0.dist-info/WHEEL
stftpitchshift-2.0.dist-info/entry_points.txt
stftpitchshift-2.0.dist-info/top_level.txt
stftpitchshift-2.0.dist-info/RECORD
