Metadata-Version: 2.1
Name: stftpitchshift
Version: 2.0
Summary: STFT based pitch and timbre shifting
Home-page: https://github.com/jurihock/stftPitchShift
Author: Juergen Hock
Author-email: juergen.hock@jurihock.de
License: MIT
Keywords: digital,audio,signal,processing,dasp,fft,stft,pitch,shifting,formants,spectrum,cepstrum,algorithms,analysis,synthesis,cpp,python
Classifier: Intended Audience :: Developers
Classifier: Intended Audience :: Education
Classifier: Intended Audience :: Other Audience
Classifier: Intended Audience :: Science/Research
Classifier: License :: OSI Approved :: MIT License
Classifier: Programming Language :: C++
Classifier: Programming Language :: Python :: 3
Classifier: Topic :: Artistic Software
Classifier: Topic :: Education
Classifier: Topic :: Multimedia :: Sound/Audio
Classifier: Topic :: Multimedia :: Sound/Audio :: Analysis
Classifier: Topic :: Multimedia :: Sound/Audio :: Sound Synthesis
Classifier: Topic :: Scientific/Engineering
Classifier: Topic :: Software Development :: Libraries
Requires-Python: >=3
License-File: LICENSE
Requires-Dist: click
Requires-Dist: matplotlib
Requires-Dist: numpy >=1.20.0
